dryxPyramid/__init__.py
dryxPyramid/__version__.py
dryxPyramid/cl_utils.py
dryxPyramid/default_settings.yaml
dryxPyramid/security.py
dryxPyramid/test_settings.yaml
dryxPyramid/utKit.py
dryxPyramid/models/__init__.py
dryxPyramid/models/models_base.py
dryxPyramid/models/models_login_post.py
dryxPyramid/renderers/__init__.py
dryxPyramid/renderers/renderer_csv.py
dryxPyramid/renderers/renderer_json.py
dryxPyramid/renderers/renderer_plain_table.py
dryxPyramid/renderers/renderer_plain_text.py
dryxPyramid/templates/__init__.py
dryxPyramid/templates/responses/__init__.py
dryxPyramid/templates/responses/templates_download.py
dryxPyramid/templates/responses/templates_login.py
dryxPyramid/views/__init__.py
dryxPyramid/views/views_base.py
dryxPyramid/views/views_base_element.py
dryxPyramid/views/views_download.py
dryxPyramid/views/views_login.py
dryxPyramid/views/views_logout.py
dryxPyramid-0.4.5.dist-info/LICENSE
dryxPyramid-0.4.5.dist-info/METADATA
dryxPyramid-0.4.5.dist-info/WHEEL
dryxPyramid-0.4.5.dist-info/top_level.txt
dryxPyramid-0.4.5.dist-info/RECORD
