Metadata-Version: 2.1
Name: dryxPyramid
Version: 0.4.5
Summary: basic, reusable code for pyramid webapps
Home-page: https://github.com/thespacedoctor/dryxPyramid
Download-URL: https://github.com/thespacedoctor/dryxPyramid/archive/v0.4.5.zip
Author: David Young
Author-email: davidrobertyoung@gmail.com
License: MIT
Keywords: pyramid, webapp
Platform: UNKNOWN
Classifier: Development Status :: 4 - Beta
Classifier: License :: OSI Approved :: MIT License
Classifier: Programming Language :: Python :: 3.7
Classifier: Topic :: Utilities
License-File: LICENSE
Requires-Dist: pyyaml
Requires-Dist: fundamentals
Requires-Dist: pyramid
Requires-Dist: sqlalchemy
Requires-Dist: passlib
Requires-Dist: paste
Requires-Dist: pymysql
Requires-Dist: khufu
Requires-Dist: numpy
